docs/Makefile
docs/__init__.py
docs/conf.py
docs/index.rst
docs/make.bat
magen_mongo-1.1a0.dist-info/DESCRIPTION.rst
magen_mongo-1.1a0.dist-info/METADATA
magen_mongo-1.1a0.dist-info/RECORD
magen_mongo-1.1a0.dist-info/WHEEL
magen_mongo-1.1a0.dist-info/metadata.json
magen_mongo-1.1a0.dist-info/top_level.txt
magen_mongo_apis/__init__.py
magen_mongo_apis/concrete_dao.py
magen_mongo_apis/mongo_core_database.py
magen_mongo_apis/mongo_exception_apis.py
magen_mongo_apis/mongo_return.py
magen_mongo_apis/mongo_utils.py
